{"node_36284_length_307_cov_0.31666":{"prefix":["NODE_36284_length_307_cov_0.316667"],"exact":[]},"node_32443_length_329_cov_0.356436":{"exact":[["NODE_32443_length_329_cov_0.356436",329,"NODE_32443_length_329_cov_0.356436",null,0,329,20000]],"prefix":[]},"node_23132_length_540_cov_":{"prefix":["NODE_23132_length_540_cov_3.745763"],"exact":[]},"node_33915_length_319_":{"prefix":["NODE_33915_length_319_cov_1.781250"],"exact":[]},"node_4611_length_55":{"exact":[],"prefix":["NODE_4611_length_5574_cov_7.449789"]},"node_18087_lengt":{"exact":[],"prefix":["NODE_18087_length_897_cov_7.042857"]},"node_33958_length_319_cov":{"exact":[],"prefix":["NODE_33958_length_319_cov_0.750000"]},"node_19590_":{"prefix":["NODE_19590_length_763_cov_1.747253"],"exact":[]},"node_14531_le":{"prefix":["NODE_14531_length_1192_cov_1.804695"],"exact":[]},"node_29427_length_356_cov_0.41921":{"exact":[],"prefix":["NODE_29427_length_356_cov_0.419214"]},"node_1064_length_17481_co":{"exact":[],"prefix":["NODE_1064_length_17481_cov_7.645730"]},"node_42381_length":{"prefix":["NODE_42381_length_284_cov_3.343949"],"exact":[]},"node_2979_length_8157_cov_7.8":{"exact":[],"prefix":["NODE_2979_length_8157_cov_7.875093"]},"node_5671_length_4403_c":{"prefix":["NODE_5671_length_4403_cov_9.829747"],"exact":[]},"node_11274_length_1635_":{"exact":[],"prefix":["NODE_11274_length_1635_cov_15.925066"]},"node_4617":{"prefix":["NODE_4617_length_5567_cov_2.859375"],"exact":[]},"node_17820_length_915_cov_4.":{"prefix":["NODE_17820_length_915_cov_4.346447"],"exact":[]},"node_1401_length_14870_cov_7.1021":{"exact":[],"prefix":["NODE_1401_length_14870_cov_7.102197"]},"node_1743_len":{"prefix":["NODE_1743_length_12751_cov_5.039211"],"exact":[]},"node_38893_length_296_c":{"prefix":["NODE_38893_length_296_cov_0.562130"],"exact":[]},"node_15629_length_":{"exact":[],"prefix":["NODE_15629_length_1087_cov_1.780208"]},"node_23972":{"prefix":["NODE_23972_length_494_cov_2.381081"],"exact":[]},"maker-node_249_length_33672_cov_7.189693-exonerate_est2genome-g":{"exact":[],"prefix":["maker-NODE_249_length_33672_cov_7.189693-exonerate_est2genome-gene-0.0","maker-NODE_249_length_33672_cov_7.189693-exonerate_est2genome-gene-0.1","maker-NODE_249_length_33672_cov_7.189693-exonerate_est2genome-gene-0.2","maker-NODE_249_length_33672_cov_7.189693-exonerate_est2genome-gene-0.3","maker-NODE_249_length_33672_cov_7.189693-exonerate_est2genome-gene-0.5"]},"node_39961_length_292_cov_1":{"exact":[],"prefix":["NODE_39961_length_292_cov_1.581818"]},"node_20460_length_702_cov_1":{"exact":[],"prefix":["NODE_20460_length_702_cov_1.354783"]},"node_35193_leng":{"exact":[],"prefix":["NODE_35193_length_312_cov_1.151351"]},"node_3595_length_6839_cov_6.302":{"exact":[],"prefix":["NODE_3595_length_6839_cov_6.302741"]},"node_6773_length_3389_cov_0.412324:hi":{"exact":[],"prefix":["NODE_6773_length_3389_cov_0.412324:hit:2615:1.3.0.0","NODE_6773_length_3389_cov_0.412324:hit:2616:1.3.0.0","NODE_6773_length_3389_cov_0.412324:hit:2617:1.3.0.0","NODE_6773_length_3389_cov_0.412324:hit:2618:1.3.0.0"]},"node_7731_length_2738_cov_5.3":{"prefix":["NODE_7731_length_2738_cov_5.387974"],"exact":[]},"node_35988_length_308_cov_":{"prefix":["NODE_35988_length_308_cov_1.779006"],"exact":[]},"node_38368_leng":{"prefix":["NODE_38368_length_298_cov_0.421053"],"exact":[]},"node_29069_length_360_co":{"exact":[],"prefix":["NODE_29069_length_360_cov_1.519313"]},"node_44543_leng":{"prefix":["NODE_44543_length_262_cov_6.651852"],"exact":[]},"node_566_length_24154_cov_7.186215:hit:434":{"exact":[],"prefix":["NODE_566_length_24154_cov_7.186215:hit:434:1.3.0.0"]},"node_8889_lengt":{"prefix":["NODE_8889_length_2240_cov_7.625177"],"exact":[]},"node_34422_length_31":{"prefix":["NODE_34422_length_316_cov_1.497354"],"exact":[]},"node_20979_length_669_cov_1.9446":{"prefix":["NODE_20979_length_669_cov_1.944649"],"exact":[]},"node_2275_leng":{"prefix":["NODE_2275_length_10338_cov_7.943786"],"exact":[]},"node_2876_length_8440_cov_7.210153:hit:8032:3.2.":{"prefix":["NODE_2876_length_8440_cov_7.210153:hit:8032:3.2.0.0"],"exact":[]},"node_18898_length_818_cov_1.358":{"exact":[],"prefix":["NODE_18898_length_818_cov_1.358900"]},"node_11265_":{"prefix":["NODE_11265_length_1637_cov_4.996689"],"exact":[]},"node_36346_length":{"prefix":["NODE_36346_length_306_cov_2.463687"],"exact":[]},"node_537_length_24706_cov_9.69107":{"exact":[],"prefix":["NODE_537_length_24706_cov_9.691078"]},"node_18237_length_886_cov_3.4":{"exact":[],"prefix":["NODE_18237_length_886_cov_3.467721"]},"node_28893_":{"prefix":["NODE_28893_length_362_cov_3.238298"],"exact":[]},"node_20013_length_":{"exact":[],"prefix":["NODE_20013_length_733_cov_1.179868"]},"node_41179_length_288_cov_1":{"exact":[],"prefix":["NODE_41179_length_288_cov_1.900621"]},"node_14616_length_1185_cov_0.3100":{"exact":[],"prefix":["NODE_14616_length_1185_cov_0.310019"]},"node_29846_length_351_cov_2.098214":{"exact":[["NODE_29846_length_351_cov_2.098214",351,"NODE_29846_length_351_cov_2.098214",null,0,351,20000]],"prefix":[]},"node_22588_length_570":{"exact":[],"prefix":["NODE_22588_length_570_cov_3.162528"]},"node_11315_l":{"prefix":["NODE_11315_length_1629_cov_4.282290"],"exact":[]},"node_21753_len":{"prefix":["NODE_21753_length_618_cov_4.059063"],"exact":[]},"node_12993_len":{"prefix":["NODE_12993_length_1364_cov_2.615198"],"exact":[]},"node_37643_length_3":{"prefix":["NODE_37643_length_300_cov_3.202312"],"exact":[]},"node_10358_length_1837_cov_2.577987:hit:6992:1.3.0.0":{"exact":[["NODE_10358_length_1837_cov_2.577987:hit:6992:1.3.0.0",0,"species:Harbinger-4_MLP|genus:DNA/PIF-Harbinger","NODE_10358_length_1837_cov_2.577987",925,1310]],"prefix":[]},"node_10324_length_1833_cov_2":{"exact":[],"prefix":["NODE_10324_length_1833_cov_2.181712","NODE_10324_length_1833_cov_2.181712:hit:3543:1.3.0.0"]},"node_35300_leng":{"exact":[],"prefix":["NODE_35300_length_311_cov_2.880435"]},"node_15033_length_1145_co":{"prefix":["NODE_15033_length_1145_cov_1.440079"],"exact":[]},"node_31442_length":{"exact":[],"prefix":["NODE_31442_length_336_cov_2.631579"]},"node_44343_length_279_cov":{"exact":[],"prefix":["NODE_44343_length_279_cov_1.098684"]},"node_3841_leng":{"exact":[],"prefix":["NODE_3841_length_6486_cov_6.747445"]},"node_7316_length_2988_cov_1.628621:hit:99:1.3.":{"prefix":["NODE_7316_length_2988_cov_1.628621:hit:99:1.3.0.0"],"exact":[]},"node_2563_":{"exact":[],"prefix":["NODE_2563_length_9338_cov_8.273506"]},"node_2644_length_9107_cov_7.365924:hit:1338:3.2.0":{"prefix":["NODE_2644_length_9107_cov_7.365924:hit:1338:3.2.0.0"],"exact":[]},"node_43208_leng":{"prefix":["NODE_43208_length_282_cov_1.870968"],"exact":[]},"node_10434_length_1811_cov_":{"exact":[],"prefix":["NODE_10434_length_1811_cov_0.346200"]},"node_34560_length_314":{"exact":[],"prefix":["NODE_34560_length_314_cov_2.585106"]},"species:(g)n|genus:simple_re":{"exact":[],"prefix":["species:(G)n|genus:Simple_repeat"]},"node_17339_length_949":{"exact":[],"prefix":["NODE_17339_length_949_cov_3.824818"]},"node_18614_length_84":{"exact":[],"prefix":["NODE_18614_length_848_cov_0.429958"]},"node_15255_length":{"prefix":["NODE_15255_length_1122_cov_3.842211"],"exact":[]},"node_29302_le":{"prefix":["NODE_29302_length_357_cov_1.317391"],"exact":[]},"node_5495_length_45":{"exact":[],"prefix":["NODE_5495_length_4586_cov_3.997085"]},"node_5545_length_4539_cov_4.199003:hit:2982:3.2.0.":{"exact":[],"prefix":["NODE_5545_length_4539_cov_4.199003:hit:2982:3.2.0.0"]},"node_37508_length_301_cov":{"exact":[],"prefix":["NODE_37508_length_301_cov_1.977011"]},"node_900_length_19086_cov_8.137665:hit:9727:3.2.0.":{"prefix":["NODE_900_length_19086_cov_8.137665:hit:9727:3.2.0.0"],"exact":[]},"node_5838_length_4243_cov_2.56001":{"exact":[],"prefix":["NODE_5838_length_4243_cov_2.560010"]},"node_30005_length_349_":{"exact":[],"prefix":["NODE_30005_length_349_cov_2.504505"]},"node_41110_length_288_cov_2.453416":{"prefix":[],"exact":[["NODE_41110_length_288_cov_2.453416",288,"NODE_41110_length_288_cov_2.453416",null,0,288,20000]]},"node_8556_leng":{"exact":[],"prefix":["NODE_8556_length_2369_cov_7.899197"]},"node_3247_length_7507_":{"exact":[],"prefix":["NODE_3247_length_7507_cov_2.978591"]},"node_19323_length_783_cov_2":{"exact":[],"prefix":["NODE_19323_length_783_cov_2.387195"]},"node_10025_length_1908":{"prefix":["NODE_10025_length_1908_cov_4.243683"],"exact":[]},"node_222_length_34856_cov_7.612122:hit:8382:3.":{"exact":[],"prefix":["NODE_222_length_34856_cov_7.612122:hit:8382:3.2.0.0"]},"node_9842_length_1956_cov_1.941498:hit:5421:1.3.0.0":{"exact":[["NODE_9842_length_1956_cov_1.941498:hit:5421:1.3.0.0",0,"species:Gypsy-5_Trm-I|genus:LTR/Gypsy","NODE_9842_length_1956_cov_1.941498",502,545]],"prefix":[]},"node_30543_length_344_":{"prefix":["NODE_30543_length_344_cov_0.529954"],"exact":[]},"node_2494":{"exact":[],"prefix":["NODE_24940_length_455_cov_2.530488","NODE_24941_length_455_cov_2.265244","NODE_24942_length_455_cov_1.237805","NODE_24943_length_455_cov_1.097561","NODE_24944_length_455_cov_1.091463","NODE_24945_length_455_cov_1.009146","NODE_24946_length_455_cov_0.798780","NODE_24947_length_455_cov_0.585366","NODE_24948_length_455_cov_0.548780","NODE_24949_length_455_cov_0.439024","NODE_2494_length_9569_cov_2.700169"]},"node_32417_":{"exact":[],"prefix":["NODE_32417_length_329_cov_0.826733"]},"node_18907_length_817_cov_1.501":{"prefix":["NODE_18907_length_817_cov_1.501449"],"exact":[]},"node_17872_length_":{"exact":[],"prefix":["NODE_17872_length_912_cov_2.188535"]},"node_39422_length_294_cov_0.85029":{"exact":[],"prefix":["NODE_39422_length_294_cov_0.850299","NODE_39422_length_294_cov_0.850299:hit:3903:1.3.0.0"]},"node_3560_length_6895_cov_5":{"exact":[],"prefix":["NODE_3560_length_6895_cov_5.217937"]},"node_23760_length_507_cov_1.255":{"exact":[],"prefix":["NODE_23760_length_507_cov_1.255263"]},"node_34899_l":{"exact":[],"prefix":["NODE_34899_length_313_cov_2.967742"]},"node_11193_length_16":{"exact":[],"prefix":["NODE_11193_length_1650_cov_2.541037"]},"node_18538_length_85":{"prefix":["NODE_18538_length_856_cov_2.613169"],"exact":[]},"node_20290_length_714_cov_0.35434":{"prefix":["NODE_20290_length_714_cov_0.354344"],"exact":[]},"node_12717_l":{"exact":[],"prefix":["NODE_12717_length_1399_cov_3.485849"]},"node_17313_length_951_cov_4.62985":{"exact":[],"prefix":["NODE_17313_length_951_cov_4.629854"]},"trinity_dn5977_c0_g1_i":{"prefix":["TRINITY_DN5977_c0_g1_i1"],"exact":[]},"node_28237_length_37":{"exact":[],"prefix":["NODE_28237_length_372_cov_3.481633"]},"node_31232_length_338_cov":{"exact":[],"prefix":["NODE_31232_length_338_cov_1.004739"]},"node_38996_length_295_cov_2":{"exact":[],"prefix":["NODE_38996_length_295_cov_2.630952"]},"species:(aaat)n|genus:s":{"prefix":["species:(AAAT)n|genus:Simple_repeat"],"exact":[]},"node_7383_length_2955_":{"exact":[],"prefix":["NODE_7383_length_2955_cov_2.025106"]},"node_21305_len":{"exact":[],"prefix":["NODE_21305_length_647_cov_2.469231"]},"node_26613_lengt":{"exact":[],"prefix":["NODE_26613_length_404_cov_0.306859"]},"node_356_length_2":{"exact":[],"prefix":["NODE_356_length_29541_cov_3.772251"]},"node_43434_l":{"exact":[],"prefix":["NODE_43434_length_281_cov_2.642857"]},"node_248_length_33676_cov_8.654386:hit:4685:3.2":{"exact":[],"prefix":["NODE_248_length_33676_cov_8.654386:hit:4685:3.2.0.0"]},"node_45845_length_134_cov_25.00":{"prefix":["NODE_45845_length_134_cov_25.000000"],"exact":[]},"node_541_length_24625_cov_7.00":{"exact":[],"prefix":["NODE_541_length_24625_cov_7.006490"]},"node_4111_length_6111_cov_8.40257":{"exact":[],"prefix":["NODE_4111_length_6111_cov_8.402574"]},"node_33203":{"prefix":["NODE_33203_length_323_cov_3.377551"],"exact":[]},"node_12785_length_1386_cov_1.27":{"prefix":["NODE_12785_length_1386_cov_1.275534"],"exact":[]},"node_40377_leng":{"prefix":["NODE_40377_length_290_cov_3.386503"],"exact":[]},"node_6441_leng":{"exact":[],"prefix":["NODE_6441_length_3668_cov_1.101384"]},"node_14522_length_1193_co":{"exact":[],"prefix":["NODE_14522_length_1193_cov_1.525328"]},"node_34901_length_3":{"prefix":["NODE_34901_length_313_cov_2.951613"],"exact":[]},"trinity_dn1212_c0_g":{"exact":[],"prefix":["TRINITY_DN1212_c0_g1_i20","TRINITY_DN1212_c0_g1_i1","TRINITY_DN1212_c0_g1_i2"]},"node_1268_length_15727_cov_9.916090:hit:3457:3.2.0.0":{"prefix":[],"exact":[["NODE_1268_length_15727_cov_9.916090:hit:3457:3.2.0.0",0,"TRINITY_DN5764_c0_g1_i1","NODE_1268_length_15727_cov_9.916090",1904,2097]]},"node_4244_length_5942_co":{"prefix":["NODE_4244_length_5942_cov_1.005847"],"exact":[]},"trinity_dn7121":{"prefix":["TRINITY_DN7121_c0_g1_i2","TRINITY_DN7121_c0_g1_i1","TRINITY_DN7121_c0_g1_i3"],"exact":[]},"node_17052_length_972_cov_1.1100":{"prefix":["NODE_17052_length_972_cov_1.110059"],"exact":[]},"node_23299_len":{"exact":[],"prefix":["NODE_23299_length_531_cov_2.371287"]},"trinity_dn7816_c0":{"exact":[],"prefix":["TRINITY_DN7816_c0_g1_i2","TRINITY_DN7816_c0_g1_i3","TRINITY_DN7816_c0_g1_i4"]},"node_23721_length_506":{"prefix":["NODE_23721_length_506_cov_2.094241"],"exact":[]},"node_11937_le":{"exact":[],"prefix":["NODE_11937_length_1517_cov_1.403597"]},"node_31685_length_334_cov_2.478":{"exact":[],"prefix":["NODE_31685_length_334_cov_2.478261"]},"node_32107_length_331_cov_1.87":{"exact":[],"prefix":["NODE_32107_length_331_cov_1.877451"]},"node_28076_l":{"exact":[],"prefix":["NODE_28076_length_375_cov_0.387097"]},"node_1315_len":{"prefix":["NODE_1315_length_15417_cov_6.820798"],"exact":[]},"node_10917_length_1708_cov_1.1771":{"prefix":["NODE_10917_length_1708_cov_1.177103"],"exact":[]},"node_1776_length_12574_cov_6.878345:hit:3095:":{"prefix":["NODE_1776_length_12574_cov_6.878345:hit:3095:3.2.0.0"],"exact":[]},"node_16855_le":{"exact":[],"prefix":["NODE_16855_length_987_cov_1.691860"]},"node_10092_length_1":{"exact":[],"prefix":["NODE_10092_length_1892_cov_3.062890","NODE_10092_length_1892_cov_3.062890:hit:8265:3.2.0.0","NODE_10092_length_1892_cov_3.062890:hit:8266:3.2.0.0"]},"node_43470_length_281_":{"exact":[],"prefix":["NODE_43470_length_281_cov_2.337662"]},"node_13453_le":{"prefix":["NODE_13453_length_1309_cov_1.808799"],"exact":[]},"node_16436_length_1020":{"prefix":["NODE_16436_length_1020_cov_1.924972"],"exact":[]},"node_24197":{"exact":[],"prefix":["NODE_24197_length_487_cov_1.536111"]},"node_31568":{"prefix":["NODE_31568_length_335_cov_2.610577"],"exact":[]},"node_31534_leng":{"prefix":["NODE_31534_length_336_cov_0.229665"],"exact":[]},"node_13362_length_1319_cov_1.77":{"prefix":["NODE_13362_length_1319_cov_1.777685"],"exact":[]},"node_41332_length_287":{"exact":[],"prefix":["NODE_41332_length_287_cov_8.893750"]},"node_25775_length_426_cov_0.95":{"exact":[],"prefix":["NODE_25775_length_426_cov_0.959866"]},"node_274_leng":{"prefix":["NODE_274_length_31840_cov_7.837485"],"exact":[]},"node_24312_length_482_cov_":{"prefix":["NODE_24312_length_482_cov_0.214085"],"exact":[]},"node_2218_length_10587_cov_7.017973:hit:5613:3":{"prefix":["NODE_2218_length_10587_cov_7.017973:hit:5613:3.2.0.0"],"exact":[]},"node_28512_length_368_cov_2.40":{"exact":[],"prefix":["NODE_28512_length_368_cov_2.402490"]},"node_11498_length_1591_cov_2.33922":{"exact":[],"prefix":["NODE_11498_length_1591_cov_2.339225"]},"node_8956_length_2220_cov_4.9":{"exact":[],"prefix":["NODE_8956_length_2220_cov_4.951266"]},"node_45801_length_136_c":{"exact":[],"prefix":["NODE_45801_length_136_cov_12.111111"]},"node_18547_lengt":{"prefix":["NODE_18547_length_855_cov_2.541209"],"exact":[]},"node_24239_length_485_cov_0.335196":{"exact":[["NODE_24239_length_485_cov_0.335196",485,"NODE_24239_length_485_cov_0.335196",null,0,485,20000]],"prefix":[]},"node_22384_length_581_cov_":{"prefix":["NODE_22384_length_581_cov_2.319383"],"exact":[]},"node_40206_length_291_cov_2.":{"exact":[],"prefix":["NODE_40206_length_291_cov_2.036585"]},"node_8777_length_2283_":{"exact":[],"prefix":["NODE_8777_length_2283_cov_2.504174"]},"node_180_length_37420_cov_9.393291:hit:4506:":{"prefix":["NODE_180_length_37420_cov_9.393291:hit:4506:3.2.0.0"],"exact":[]},"node_24797_length_461_cov_9.12":{"prefix":["NODE_24797_length_461_cov_9.125749"],"exact":[]},"node_38438_":{"prefix":["NODE_38438_length_297_cov_2.741176"],"exact":[]},"node_3717_length":{"exact":[],"prefix":["NODE_3717_length_6641_cov_3.889469"]},"node_36281_length_3":{"prefix":["NODE_36281_length_307_cov_0.377778"],"exact":[]},"node_2101_length_11056_cov_":{"exact":[],"prefix":["NODE_2101_length_11056_cov_7.574526"]},"node_3289_len":{"prefix":["NODE_3289_length_7393_cov_7.522296","NODE_3289_length_7393_cov_7.522296:hit:536:3.2.0.0","NODE_3289_length_7393_cov_7.522296:hit:556:3.2.0.0","NODE_3289_length_7393_cov_7.522296:hit:537:3.2.0.0","NODE_3289_length_7393_cov_7.522296:hit:557:3.2.0.0","NODE_3289_length_7393_cov_7.522296:hit:539:3.2.0.0","NODE_3289_length_7393_cov_7.522296:hit:541:3.2.0.0","NODE_3289_length_7393_cov_7.522296:hit:545:3.2.0.0","NODE_3289_length_7393_cov_7.522296:hit:559:3.2.0.0","NODE_3289_length_7393_cov_7.522296:hit:561:3.2.0.0","NODE_3289_length_7393_cov_7.522296:hit:565:3.2.0.0","NODE_3289_length_7393_cov_7.522296:hit:538:3.2.0.0","NODE_3289_length_7393_cov_7.522296:hit:540:3.2.0.0","NODE_3289_length_7393_cov_7.522296:hit:542:3.2.0.0","NODE_3289_length_7393_cov_7.522296:hit:544:3.2.0.0","NODE_3289_length_7393_cov_7.522296:hit:558:3.2.0.0","NODE_3289_length_7393_cov_7.522296:hit:560:3.2.0.0","NODE_3289_length_7393_cov_7.522296:hit:562:3.2.0.0","NODE_3289_length_7393_cov_7.522296:hit:564:3.2.0.0","NODE_3289_length_7393_cov_7.522296:hit:543:3.2.0.0",{"name":"too many matches","hitLimit":1}],"exact":[]},"node_37934_":{"exact":[],"prefix":["NODE_37934_length_299_cov_2.755814"]},"node_7697_l":{"prefix":["NODE_7697_length_2756_cov_7.047547"],"exact":[]},"node_29033_length_360_co":{"prefix":["NODE_29033_length_360_cov_3.171674"],"exact":[]},"node_1999":{"exact":[],"prefix":["NODE_19990_length_735_cov_1.041118","NODE_19991_length_734_cov_15.561779","NODE_19992_length_734_cov_10.252059","NODE_19993_length_737_cov_9.421746","NODE_19994_length_734_cov_3.072488","NODE_19995_length_734_cov_2.469522","NODE_19996_length_734_cov_2.354201","NODE_19997_length_730_cov_1.756178","NODE_19998_length_734_cov_1.464580","NODE_19999_length_735_cov_1.029654","NODE_1999_length_11460_cov_10.889261","NODE_19994_length_734_cov_3.072488:hit:2234:3.2.0.0","NODE_19994_length_734_cov_3.072488:hit:2233:3.2.0.0","NODE_1999_length_11460_cov_10.889261:hit:5732:1.3.0.0","NODE_1999_length_11460_cov_10.889261:hit:5733:1.3.0.0","NODE_1999_length_11460_cov_10.889261:hit:5734:1.3.0.0","NODE_1999_length_11460_cov_10.889261:hit:5735:1.3.0.0","NODE_1999_length_11460_cov_10.889261:hit:5740:3.2.0.0","NODE_1999_length_11460_cov_10.889261:hit:5738:3.2.0.0","NODE_1999_length_11460_cov_10.889261:hit:5739:3.2.0.0",{"name":"too many matches","hitLimit":1}]},"node_7651_length_":{"prefix":["NODE_7651_length_2791_cov_11.982357"],"exact":[]},"node_40889_length_289_cov_":{"exact":[],"prefix":["NODE_40889_length_289_cov_1.037037"]},"species:(tgatgga)n|genus:simple_":{"exact":[],"prefix":["species:(TGATGGA)n|genus:Simple_repeat"]},"node_14311_length_12":{"prefix":["NODE_14311_length_1213_cov_4.744015"],"exact":[]},"node_20986_length_":{"prefix":["NODE_20986_length_669_cov_0.352399","NODE_20986_length_669_cov_0.352399:hit:5831:1.3.0.0","NODE_20986_length_669_cov_0.352399:hit:5832:1.3.0.0"],"exact":[]},"node_40036_l":{"exact":[],"prefix":["NODE_40036_length_292_cov_0.575758"]},"node_41217_length_288_cov_1.1":{"exact":[],"prefix":["NODE_41217_length_288_cov_1.142857"]},"node_36569_length_305_cov_2.74719":{"exact":[],"prefix":["NODE_36569_length_305_cov_2.747191"]},"node_35745_length_309_cov_2.6":{"prefix":["NODE_35745_length_309_cov_2.631868"],"exact":[]},"node_13746":{"prefix":["NODE_13746_length_1275_cov_1.472997"],"exact":[]},"node_39958_length_292_cov_1.59393":{"prefix":["NODE_39958_length_292_cov_1.593939"],"exact":[]},"node_2257_length_10386_cov":{"prefix":["NODE_2257_length_10386_cov_9.775612"],"exact":[]},"node_32209_length_330_cov_":{"prefix":["NODE_32209_length_330_cov_2.817734"],"exact":[]},"node_9764_length_1974_co":{"exact":[],"prefix":["NODE_9764_length_1974_cov_9.565241"]},"node_7020_length_3202_cov_1.":{"prefix":["NODE_7020_length_3202_cov_1.595447"],"exact":[]},"node_195_length_36289_cov_5.6786":{"prefix":["NODE_195_length_36289_cov_5.678603"],"exact":[]},"node_7530_length_2860_cov_2.1430":{"exact":[],"prefix":["NODE_7530_length_2860_cov_2.143066"]},"node_42637_len":{"exact":[],"prefix":["NODE_42637_length_284_cov_0.592357"]},"node_26497_length_406_cov_2":{"exact":[],"prefix":["NODE_26497_length_406_cov_2.426523"]},"node_2704_le":{"exact":[],"prefix":["NODE_2704_length_8870_cov_9.694568"]},"node_21258_length_650_cov_1.":{"prefix":["NODE_21258_length_650_cov_1.351816"],"exact":[]},"node_29021_length_360_co":{"prefix":["NODE_29021_length_360_cov_8.987124"],"exact":[]},"node_1409_length_14824_co":{"prefix":["NODE_1409_length_14824_cov_7.545962"],"exact":[]},"node_8255_length_2498_cov_5.285":{"prefix":["NODE_8255_length_2498_cov_5.285112"],"exact":[]},"node_4295_l":{"exact":[],"prefix":["NODE_4295_length_5882_cov_6.837533"]},"node_9168_length_2145_cov_6.8":{"prefix":["NODE_9168_length_2145_cov_6.894945"],"exact":[]},"node_25245_":{"exact":[],"prefix":["NODE_25245_length_443_cov_1.898734"]},"node_31308_length_337_cov_3.":{"exact":[],"prefix":["NODE_31308_length_337_cov_3.052381"]},"node_39802_length_292_cov_5.3":{"prefix":["NODE_39802_length_292_cov_5.339394"],"exact":[]},"node_38521_length_297_cov_":{"prefix":["NODE_38521_length_297_cov_1.976471"],"exact":[]},"node_25885_length_4":{"exact":[],"prefix":["NODE_25885_length_422_cov_2.932203"]},"node_23424_length_524_cov_3.":{"exact":[],"prefix":["NODE_23424_length_524_cov_3.171285"]},"node_3765_length_6579_cov_8.3541":{"prefix":["NODE_3765_length_6579_cov_8.354154"],"exact":[]},"node_1922_length_11851_c":{"exact":[],"prefix":["NODE_1922_length_11851_cov_1.631247"]},"node_18390_length_":{"prefix":["NODE_18390_length_872_cov_8.876510"],"exact":[]},"node_42156_length_285_cov_2":{"prefix":["NODE_42156_length_285_cov_2.107595"],"exact":[]},"node_39351_le":{"prefix":["NODE_39351_length_294_cov_1.940120"],"exact":[]},"node_3876_length_6433_cov_9.674596:hit:1564:1.3.":{"prefix":["NODE_3876_length_6433_cov_9.674596:hit:1564:1.3.0.0"],"exact":[]},"node_3586_length_6852_cov_8.058885:hit:298:3":{"prefix":["NODE_3586_length_6852_cov_8.058885:hit:298:3.2.0.0"],"exact":[]},"node_33644_length_321_cov_0.742268":{"exact":[["NODE_33644_length_321_cov_0.742268",321,"NODE_33644_length_321_cov_0.742268",null,0,321,20000]],"prefix":[]},"node_26737_l":{"exact":[],"prefix":["NODE_26737_length_401_cov_0.430657"]},"node_13950_length_1251_cov_2.64":{"exact":[],"prefix":["NODE_13950_length_1251_cov_2.644128"]},"node_45217_length_":{"prefix":["NODE_45217_length_215_cov_36.431818"],"exact":[]},"node_7240_length_3043_cov_1.122":{"exact":[],"prefix":["NODE_7240_length_3043_cov_1.122771"]},"node_12551_length":{"exact":[],"prefix":["NODE_12551_length_1423_cov_4.103395"]},"node_42538_length_284_cov_1.7":{"prefix":["NODE_42538_length_284_cov_1.777070"],"exact":[]},"node_32865":{"exact":[],"prefix":["NODE_32865_length_326_cov_0.482412"]},"node_12569_len":{"prefix":["NODE_12569_length_1419_cov_15.306502"],"exact":[]},"node_8426_length_":{"exact":[],"prefix":["NODE_8426_length_2430_cov_1.149805"]},"node_34934_leng":{"exact":[],"prefix":["NODE_34934_length_313_cov_2.338710"]},"node_7840_":{"exact":[],"prefix":["NODE_7840_length_2681_cov_11.223179"]},"node_62_length_51960_cov_7.032547:hit:9343:3.2.":{"prefix":["NODE_62_length_51960_cov_7.032547:hit:9343:3.2.0.0"],"exact":[]},"node_45182_length_227_c":{"prefix":["NODE_45182_length_227_cov_17.790000"],"exact":[]},"node_23944_length_49":{"exact":[],"prefix":["NODE_23944_length_499_cov_0.736559"]},"node_36268_length_":{"exact":[],"prefix":["NODE_36268_length_307_cov_0.455556"]},"node_4013_length":{"exact":[],"prefix":["NODE_4013_length_6238_cov_8.411553"]},"node_45856_length_134_cov_1.285714":{"prefix":[],"exact":[["NODE_45856_length_134_cov_1.285714",134,"NODE_45856_length_134_cov_1.285714",null,0,134,20000]]},"node_6264_le":{"exact":[],"prefix":["NODE_6264_length_3826_cov_4.703704"]},"node_30464_length_344_cov_6.013":{"prefix":["NODE_30464_length_344_cov_6.013825"],"exact":[]},"node_21212_length_652_cov_1.5969":{"exact":[],"prefix":["NODE_21212_length_652_cov_1.596958"]},"node_5477_length_4605_cov_8.285842:hit:9880:":{"prefix":["NODE_5477_length_4605_cov_8.285842:hit:9880:3.2.0.0"],"exact":[]},"node_41849_length_286_cov_1":{"exact":[],"prefix":["NODE_41849_length_286_cov_1.905660"]},"node_23565_length_517_cov_2.61794":{"exact":[],"prefix":["NODE_23565_length_517_cov_2.617949"]},"node_34625_length_315_cov_1.276":{"exact":[],"prefix":["NODE_34625_length_315_cov_1.276596","NODE_34625_length_315_cov_1.276596:hit:3277:1.3.0.0"]},"node_5666_le":{"prefix":["NODE_5666_length_4407_cov_1.541355"],"exact":[]},"node_25335_l":{"exact":[],"prefix":["NODE_25335_length_440_cov_2.431310"]},"node_14920_length_1154_cov_3.775":{"exact":[],"prefix":["NODE_14920_length_1154_cov_3.775073"]},"node_1306_le":{"prefix":["NODE_1306_length_15487_cov_5.594234"],"exact":[]},"node_11103_length_1666_":{"exact":[],"prefix":["NODE_11103_length_1666_cov_7.510071"]},"node_35080":{"prefix":["NODE_35080_length_312_cov_3.248649"],"exact":[]},"node_444_length_27079":{"prefix":["NODE_444_length_27079_cov_8.046267"],"exact":[]},"node_37214_length_302_":{"exact":[],"prefix":["NODE_37214_length_302_cov_2.577143"]},"trinity_dn9778_c0_g1_":{"prefix":["TRINITY_DN9778_c0_g1_i1"],"exact":[]},"node_27590_length_383_":{"exact":[],"prefix":["NODE_27590_length_383_cov_1.218750"]},"node_8712_lengt":{"prefix":["NODE_8712_length_2305_cov_3.074839"],"exact":[]},"node_39370_length_294":{"exact":[],"prefix":["NODE_39370_length_294_cov_1.658683"]},"node_220_length_34931_cov_9.4":{"prefix":["NODE_220_length_34931_cov_9.458769"],"exact":[]},"node_8322_length_2468_cov_0.494660:hit:21:3.2.":{"exact":[],"prefix":["NODE_8322_length_2468_cov_0.494660:hit:21:3.2.0.0"]},"node_4388_length_5795_co":{"exact":[],"prefix":["NODE_4388_length_5795_cov_8.112032"]},"node_42756_length_283_c":{"exact":[],"prefix":["NODE_42756_length_283_cov_2.807692"]},"node_2167_length_10783_cov":{"exact":[],"prefix":["NODE_2167_length_10783_cov_7.468375"]},"node_1610_length_13489_cov_9.151998:hit:5566:3":{"prefix":["NODE_1610_length_13489_cov_9.151998:hit:5566:3.2.0.0"],"exact":[]},"node_227_length_34491_cov_7.920469":{"prefix":[],"exact":[["NODE_227_length_34491_cov_7.920469",34491,"NODE_227_length_34491_cov_7.920469",null,0,34491,20000]]},"node_27961_length_376":{"exact":[],"prefix":["NODE_27961_length_376_cov_3.586345"]},"node_19494_length_770_cov_":{"prefix":["NODE_19494_length_770_cov_1.804044"],"exact":[]},"node_2644_length_9107_cov_7.365924:hit:1309:1.3.0.0":{"prefix":[],"exact":[["NODE_2644_length_9107_cov_7.365924:hit:1309:1.3.0.0",0,"species:(ATG)n|genus:Simple_repeat","NODE_2644_length_9107_cov_7.365924",5062,5207]]},"node_9485_length_2047_cov_1.742708":{"exact":[["NODE_9485_length_2047_cov_1.742708",2047,"NODE_9485_length_2047_cov_1.742708",null,0,2047,20000]],"prefix":[]},"node_40799_":{"prefix":["NODE_40799_length_289_cov_2.327160"],"exact":[]},"node_10644_length_":{"exact":[],"prefix":["NODE_10644_length_1764_cov_1.977398"]},"node_13320_length_1324_cov_4.2":{"exact":[],"prefix":["NODE_13320_length_1324_cov_4.218881"]},"node_39975_len":{"prefix":["NODE_39975_length_292_cov_1.248485"],"exact":[]},"node_28818_length_364_cov_0.4641":{"prefix":["NODE_28818_length_364_cov_0.464135"],"exact":[]},"node_5510_length_4572_cov_8.259393:hit:2523:3.2.0.0":{"prefix":[],"exact":[["NODE_5510_length_4572_cov_8.259393:hit:2523:3.2.0.0",0,"TRINITY_DN7791_c0_g1_i6","NODE_5510_length_4572_cov_8.259393",0,185]]},"node_26907_length_397_cov_0.533333":{"prefix":[],"exact":[["NODE_26907_length_397_cov_0.533333",397,"NODE_26907_length_397_cov_0.533333",null,0,397,20000]]},"node_19683_length_756":{"prefix":["NODE_19683_length_756_cov_3.731320"],"exact":[]},"node_43189_length_282_cov_2.00645":{"prefix":["NODE_43189_length_282_cov_2.006452"],"exact":[]},"node_37812_length_300_cov_0.693642":{"prefix":[],"exact":[["NODE_37812_length_300_cov_0.693642",300,"NODE_37812_length_300_cov_0.693642",null,0,300,20000]]},"node_22217_length_591_co":{"prefix":["NODE_22217_length_591_cov_2.370690"],"exact":[]},"node_27551_length_384":{"prefix":["NODE_27551_length_384_cov_0.891051"],"exact":[]},"node_10051_le":{"exact":[],"prefix":["NODE_10051_length_1901_cov_5.049042","NODE_10051_length_1901_cov_5.049042:hit:1750:1.3.0.0"]},"node_24074_length_492_cov_24.50137":{"exact":[],"prefix":["NODE_24074_length_492_cov_24.501370"]},"node_29205_length_358_cov_2.445":{"prefix":["NODE_29205_length_358_cov_2.445887"],"exact":[]},"node_31616_l":{"exact":[],"prefix":["NODE_31616_length_335_cov_0.740385"]},"node_43815_length_280_":{"prefix":["NODE_43815_length_280_cov_2.418301"],"exact":[]},"node_14399_length_1205_cov_2":{"exact":[],"prefix":["NODE_14399_length_1205_cov_2.205009"]},"node_26576_length_404_cov":{"prefix":["NODE_26576_length_404_cov_3.862816"],"exact":[]},"node_35287_len":{"exact":[],"prefix":["NODE_35287_length_311_cov_3.108696"]},"node_16966_length_97":{"prefix":["NODE_16966_length_978_cov_9.081081"],"exact":[]},"node_31991_le":{"prefix":["NODE_31991_length_332_cov_0.682927"],"exact":[]},"node_37195_le":{"exact":[],"prefix":["NODE_37195_length_302_cov_2.868571"]},"node_7172_length_3084_cov_23.7":{"exact":[],"prefix":["NODE_7172_length_3084_cov_23.728103"]},"node_42043_":{"prefix":["NODE_42043_length_285_cov_3.056962"],"exact":[]},"node_17133_le":{"prefix":["NODE_17133_length_965_cov_4.454654"],"exact":[]},"node_2818_l":{"prefix":["NODE_2818_length_8568_cov_9.906054"],"exact":[]},"node_843_length_19750_cov_8.684503:hit:7323:3":{"prefix":["NODE_843_length_19750_cov_8.684503:hit:7323:3.2.0.0"],"exact":[]},"node_33205_length_":{"prefix":["NODE_33205_length_323_cov_3.280612"],"exact":[]},"node_45485_length":{"exact":[],"prefix":["NODE_45485_length_168_cov_176.463415"]},"species:academh-6_pgr|genus:dna/acad":{"exact":[],"prefix":["species:AcademH-6_PGr|genus:DNA/Academ-H"]},"node_22541_length_573_cov_1":{"exact":[],"prefix":["NODE_22541_length_573_cov_1.556054"]},"node_21219_length_652_":{"exact":[],"prefix":["NODE_21219_length_652_cov_2.790476"]},"node_22221_length_591_co":{"prefix":["NODE_22221_length_591_cov_2.129310"],"exact":[]},"node_24020_length_495_cov_":{"prefix":["NODE_24020_length_495_cov_2.809783"],"exact":[]},"node_17960_length_9":{"exact":[],"prefix":["NODE_17960_length_906_cov_6.915276","NODE_17960_length_906_cov_6.915276:hit:6068:3.2.0.0","NODE_17960_length_906_cov_6.915276:hit:6067:3.2.0.0"]},"node_15551_length_1093_cov_5.333333:hit:5637:3":{"exact":[],"prefix":["NODE_15551_length_1093_cov_5.333333:hit:5637:3.2.0.0"]},"node_32409_length_329_cov":{"prefix":["NODE_32409_length_329_cov_0.940594"],"exact":[]},"node_39953_l":{"prefix":["NODE_39953_length_292_cov_1.684848"],"exact":[]},"node_41943_leng":{"exact":[],"prefix":["NODE_41943_length_286_cov_0.572327"]},"node_32214_l":{"exact":[],"prefix":["NODE_32214_length_330_cov_2.694581"]},"node_33802_length_320_c":{"exact":[],"prefix":["NODE_33802_length_320_cov_0.492228"]},"node_25257_length_435_cov_1.1898":{"prefix":["NODE_25257_length_435_cov_1.189873"],"exact":[]},"node_34597_le":{"prefix":["NODE_34597_length_315_cov_1.962766"],"exact":[]},"node_14609_length_1185_cov_3.16351":{"prefix":["NODE_14609_length_1185_cov_3.163516"],"exact":[]},"node_20704_length_68":{"prefix":["NODE_20704_length_686_cov_1.406082"],"exact":[]},"node_16692_length_999_cov":{"prefix":["NODE_16692_length_999_cov_3.993119"],"exact":[]},"node_28792_length_364_cov_1.409283":{"exact":[["NODE_28792_length_364_cov_1.409283",364,"NODE_28792_length_364_cov_1.409283",null,0,364,20000]],"prefix":[]},"node_2049_length_11281_cov_6.96":{"prefix":["NODE_2049_length_11281_cov_6.962525"],"exact":[]},"node_10842_length_1723_cov_3.2":{"exact":[],"prefix":["NODE_10842_length_1723_cov_3.263784"]},"node_9376_length_2081_cov_2.6":{"exact":[],"prefix":["NODE_9376_length_2081_cov_2.643808"]},"node_23132_length_540_cov_3.":{"prefix":["NODE_23132_length_540_cov_3.745763"],"exact":[]},"node_699_length_":{"exact":[],"prefix":["NODE_699_length_21662_cov_7.481913"]},"node_31511_length_336_cov_0.":{"exact":[],"prefix":["NODE_31511_length_336_cov_0.569378"]},"node_17998_l":{"prefix":["NODE_17998_length_904_cov_2.217503"],"exact":[]},"node_22314":{"exact":[],"prefix":["NODE_22314_length_585_cov_2.048035"]},"node_8495_length_2395_cov_1.5290":{"prefix":["NODE_8495_length_2395_cov_1.529075"],"exact":[]},"node_24796_length_462_cov_0.4238":{"prefix":["NODE_24796_length_462_cov_0.423881"],"exact":[]},"node_11450_length_1":{"exact":[],"prefix":["NODE_11450_length_1606_cov_1.381339"]},"node_11416_length_1610_cov_8.28":{"prefix":["NODE_11416_length_1610_cov_8.286581"],"exact":[]},"node_15209_length":{"exact":[],"prefix":["NODE_15209_length_1126_cov_2.922923"]},"node_4885_length_52":{"prefix":["NODE_4885_length_5227_cov_10.043333"],"exact":[]},"node_41976_length":{"exact":[],"prefix":["NODE_41976_length_286_cov_0.415094"]},"node_42261_len":{"exact":[],"prefix":["NODE_42261_length_285_cov_0.759494"]},"node_41048_length_288_cov":{"prefix":["NODE_41048_length_288_cov_3.111801"],"exact":[]},"node_31875_length_333_cov_0.":{"prefix":["NODE_31875_length_333_cov_0.349515"],"exact":[]},"node_15976_length_1060_cov_2.106109:hit":{"prefix":["NODE_15976_length_1060_cov_2.106109:hit:2363:3.2.0.0","NODE_15976_length_1060_cov_2.106109:hit:2364:3.2.0.0","NODE_15976_length_1060_cov_2.106109:hit:2361:3.2.0.0","NODE_15976_length_1060_cov_2.106109:hit:2362:3.2.0.0"],"exact":[]},"node_10679_length_1757_cov_3.457055":{"prefix":[],"exact":[["NODE_10679_length_1757_cov_3.457055",1757,"NODE_10679_length_1757_cov_3.457055",null,0,1757,20000]]},"node_13250_length_1333_cov_9.3739":{"exact":[],"prefix":["NODE_13250_length_1333_cov_9.373964"]},"trinity_dn1012_c0":{"prefix":["TRINITY_DN1012_c0_g1_i11","TRINITY_DN1012_c0_g1_i15","TRINITY_DN1012_c0_g1_i5","TRINITY_DN1012_c0_g1_i7","TRINITY_DN1012_c0_g1_i14","TRINITY_DN1012_c0_g1_i9","TRINITY_DN1012_c0_g1_i1","TRINITY_DN1012_c0_g1_i10","TRINITY_DN1012_c0_g1_i2","TRINITY_DN1012_c0_g1_i13","TRINITY_DN1012_c0_g1_i4","TRINITY_DN1012_c0_g1_i12","TRINITY_DN1012_c0_g1_i8","TRINITY_DN1012_c0_g1_i6","TRINITY_DN1012_c0_g1_i16"],"exact":[]},"node_30792_length_341_cov_3":{"exact":[],"prefix":["NODE_30792_length_341_cov_3.817757"]},"node_1199_leng":{"prefix":["NODE_1199_length_16184_cov_7.233551"],"exact":[]},"node_37864_length_300_c":{"prefix":["NODE_37864_length_300_cov_0.184971"],"exact":[]},"node_5154_length_4928_":{"prefix":["NODE_5154_length_4928_cov_2.183503"],"exact":[]},"node_18174_length_891":{"prefix":["NODE_18174_length_891_cov_0.302356"],"exact":[]},"node_36613_length_305_cov_2.2":{"exact":[],"prefix":["NODE_36613_length_305_cov_2.241573"]},"node_12590_length_141":{"prefix":["NODE_12590_length_1417_cov_2.325581"],"exact":[]},"node_37732_length_300_cov_1.79190":{"exact":[],"prefix":["NODE_37732_length_300_cov_1.791908"]},"node_11425_length_1609_cov_2.261":{"prefix":["NODE_11425_length_1609_cov_2.261134"],"exact":[]}}